lt25-0.1.2.dist-info/licenses/LICENSE
protocol/ActiveDisplay_pb2.py
protocol/AudioStatus_pb2.py
protocol/AuditionPresetStatus_pb2.py
protocol/AuditionPreset_pb2.py
protocol/AuditionStateRequest_pb2.py
protocol/AuditionStateStatus_pb2.py
protocol/ClearPresetStatus_pb2.py
protocol/ClearPreset_pb2.py
protocol/ConnectionStatusRequest_pb2.py
protocol/ConnectionStatus_pb2.py
protocol/CurrentDisplayedPresetIndexStatus_pb2.py
protocol/CurrentLoadedPresetIndexBypassStatus_pb2.py
protocol/CurrentLoadedPresetIndexStatus_pb2.py
protocol/CurrentPresetRequest_pb2.py
protocol/CurrentPresetSet_pb2.py
protocol/CurrentPresetStatus_pb2.py
protocol/DspUnitParameterStatus_pb2.py
protocol/ExitAuditionPresetStatus_pb2.py
protocol/ExitAuditionPreset_pb2.py
protocol/FenderMessageLT_pb2.py
protocol/FirmwareVersionRequest_pb2.py
protocol/FirmwareVersionStatus_pb2.py
protocol/FrameBufferMessageRequest_pb2.py
protocol/FrameBufferMessage_pb2.py
protocol/Heartbeat_pb2.py
protocol/IndexButton_pb2.py
protocol/IndexEncoder_pb2.py
protocol/IndexPot_pb2.py
protocol/LT4FootswitchModeRequest_pb2.py
protocol/LT4FootswitchModeStatus_pb2.py
protocol/LineOutGainRequest_pb2.py
protocol/LineOutGainSet_pb2.py
protocol/LineOutGainStatus_pb2.py
protocol/LoadPreset_TestSuite_pb2.py
protocol/LoadPreset_pb2.py
protocol/LoopbackTest_pb2.py
protocol/MemoryUsageRequest_pb2.py
protocol/MemoryUsageStatus_pb2.py
protocol/ModalStatusMessage_pb2.py
protocol/NewPresetSavedStatus_pb2.py
protocol/PresetJSONMessageRequest_LT_pb2.py
protocol/PresetJSONMessage_pb2.py
protocol/PresetSavedStatus_pb2.py
protocol/ProcessorUtilizationRequest_pb2.py
protocol/ProcessorUtilization_pb2.py
protocol/ProductIdentificationRequest_pb2.py
protocol/ProductIdentificationStatus_pb2.py
protocol/QASlotsRequest_pb2.py
protocol/QASlotsSet_pb2.py
protocol/QASlotsStatus_pb2.py
protocol/RenamePresetAt_pb2.py
protocol/ReplaceNodeStatus_pb2.py
protocol/ReplaceNode_pb2.py
protocol/RetrievePreset_pb2.py
protocol/SaveCurrentPresetTo_pb2.py
protocol/SaveCurrentPreset_pb2.py
lt25-0.1.2.dist-info/METADATA
lt25-0.1.2.dist-info/WHEEL
lt25-0.1.2.dist-info/top_level.txt
lt25-0.1.2.dist-info/RECORD
